flamo/__init__.py
flamo/functional.py
flamo/utils.py
flamo/auxiliary/__init__.py
flamo/auxiliary/eq.py
flamo/auxiliary/filterbank.py
flamo/auxiliary/minimize.py
flamo/auxiliary/reverb.py
flamo/auxiliary/scattering.py
flamo/auxiliary/velvet.py
flamo/auxiliary/config/config.py
flamo/optimize/__init__.py
flamo/optimize/dataset.py
flamo/optimize/loss.py
flamo/optimize/surface.py
flamo/optimize/trainer.py
flamo/optimize/utils.py
flamo/processor/__init__.py
flamo/processor/dsp.py
flamo/processor/system.py
flamo-0.2.9.dist-info/METADATA
flamo-0.2.9.dist-info/WHEEL
flamo-0.2.9.dist-info/licenses/LICENSE
flamo-0.2.9.dist-info/RECORD
