Metadata-Version: 2.4
Name: flamo
Version: 0.2.9
Summary: An Open-Source Library for Frequency-Domain Differentiable Audio Processing
Project-URL: Homepage, https://github.com/gdalsanto/flamo
Project-URL: Issues, https://github.com/gdalsanto/flamo/issues
Author-email: Gloria Dal Santo <gloria.dalsanto@aalto.fi>, Gian Marco De Bortoli <gian.debortoli@aalto.fi>, "Sebastian J. Schlecht" <sebastian.schlecht@fau.de>
Maintainer-email: Gloria Dal Santo <gloria.dalsanto@aalto.fi>, Gian Marco De Bortoli <gian.debortoli@aalto.fi>
License: MIT License
License-File: LICENSE
Keywords: audio,differentiable programming,machine learning,optimization,signal processing
Classifier: License :: OSI Approved :: MIT License
Classifier: Programming Language :: Python :: 3
Requires-Python: >=3.10
Requires-Dist: matplotlib
Requires-Dist: nnaudio
Requires-Dist: numpy
Requires-Dist: pydantic
Requires-Dist: pyfar
Requires-Dist: pysoundfile
Requires-Dist: pyyaml
Requires-Dist: scipy
Requires-Dist: torch
Requires-Dist: torchaudio
Requires-Dist: tqdm
